alphaPredict/.DS_Store
alphaPredict/__init__.py
alphaPredict/_version.py
alphaPredict/alpha.py
alphaPredict/alpha_exceptions.py
alphaPredict/backend/.DS_Store
alphaPredict/backend/alpha_graph.py
alphaPredict/backend/alpha_tools.py
alphaPredict/backend/brnn_architecture.py
alphaPredict/backend/encode_sequence.py
alphaPredict/backend/parrot_alpha.py
alphaPredict/backend/networks/.DS_Store
alphaPredict/backend/networks/alpha_fold_networkV1.pt
alphaPredict/backend/networks/alpha_fold_networkV2.pt
alphaPredict/backend/networks/alpha_fold_networkV4_hs20_nL2_200e_all_prot.pt
alphaPredict/backend/networks/alpha_fold_networkV5_hs40_nL5_200e_all_prot.pt
alphaPredict/backend/networks/alpha_fold_networkV6_hs40_nL2_200e_all_prot.pt
alphaPredict/backend/networks/alpha_fold_networkV7_hs100_nL2_200e_all_prot.pt
alphaPredict/data/README.md
alphaPredict/data/look_and_say.dat
alphaPredict/tests/__init__.py
alphaPredict/tests/test_alphaPredict.py
alphaPredict-1.3.0.dist-info/LICENSE
alphaPredict-1.3.0.dist-info/METADATA
alphaPredict-1.3.0.dist-info/WHEEL
alphaPredict-1.3.0.dist-info/top_level.txt
alphaPredict-1.3.0.dist-info/RECORD
