Metadata-Version: 2.1
Name: alphaPredict
Version: 1.3.0
Summary: alphaPredict: A predictor of AlphaFold2 confidence scores
Author-email: Ryan Emenecker <remenecker@wustl.edu>
License: MIT
Requires-Python: >=3.8
License-File: LICENSE
Requires-Dist: numpy
Requires-Dist: matplotlib
Requires-Dist: torch
Provides-Extra: test
Requires-Dist: pytest >=6.1.2 ; extra == 'test'
